dscleaner/__init__.py
dscleaner/__main__.py
dscleaner/csvfileinfo.py
dscleaner/fileinfo.py
dscleaner/fileutil.py
dscleaner/filewriter.py
dscleaner/ifileinfo.py
dscleaner/merger.py
dscleaner/splitter.py
dscleaner/utils.py
dscleaner-0.2.0.dist-info/LICENSE
dscleaner-0.2.0.dist-info/METADATA
dscleaner-0.2.0.dist-info/WHEEL
dscleaner-0.2.0.dist-info/top_level.txt
dscleaner-0.2.0.dist-info/RECORD
