Metadata-Version: 2.1
Name: dscleaner
Version: 0.2.0
Summary: A Python Library to Clean, Preprocess and Convert audio datasets
Home-page: UNKNOWN
Author: Manuel Pereira
Author-email: afonso.pereira4525@gmail.com
License: The MIT License
Project-URL: Documentation, https://dscleaner.rtfd.io/
Project-URL: Source code, https://gitlab.com/ManelPereira/dscleaner
Project-URL: Examples, https://osf.io/vraqz/
Platform: UNKNOWN
Requires-Dist: PySoundFile (>=0.9.0.post1)
Requires-Dist: librosa (>=0.6.3)
Requires-Dist: numpy (>=1.16.1)
Requires-Dist: pandas (>=0.24.1)
Requires-Dist: click
Requires-Dist: natsort
Requires-Dist: pyemddf
